unicornafl/__init__.py
unicornafl/unicornafl.py
unicornafl/lib/libunicornafl.so
unicornafl-2.1.0.dist-info/METADATA
unicornafl-2.1.0.dist-info/WHEEL
unicornafl-2.1.0.dist-info/top_level.txt
unicornafl-2.1.0.dist-info/RECORD
