Metadata-Version: 2.1
Name: unicornafl
Version: 2.1.0
Summary: Unicornafl
Home-page: https://github.com/AFLplusplus/unicornafl
Author: Lazymio
Author-email: mio@lazym.io
License: UNKNOWN
Platform: UNKNOWN
Classifier: License :: OSI Approved :: BSD License
Classifier: Programming Language :: Python :: 3
Requires: ctypes
Provides: unicornafl
Requires-Dist: unicorn >=2.0.1
